oak/.DS_Store
oak/__init__.py
oak/celery_app.py
oak/config.py
oak/main.py
oak/modules/.DS_Store
oak/modules/__init__.py
oak/modules/user/__init__.py
oak/modules/user/goals.py
oak/modules/user/portfolio.py
oak/prompt/library/sample.jinja2
oak/prompt/shared_templates/base_template.jinja2
oak/prompt/shared_templates/footer.jinja2
oak/prompt/shared_templates/header.jinja2
oak/services/.DS_Store
oak/services/__init__.py
oak/services/data_fetcher/.DS_Store
oak/services/data_fetcher/__init__.py
oak/services/data_fetcher/api_service/__init__.py
oak/services/data_fetcher/api_service/api_service.py
oak/services/data_fetcher/api_service/library/__init__.py
oak/services/data_fetcher/api_service/library/stocks/__init__.py
oak/services/data_fetcher/api_service/library/stocks/fetch_stock_daily_summary.py
oak/services/data_fetcher/api_service/library/stocks/fetch_stock_data.py
oak/services/data_fetcher/api_service/library/stocks/fetch_stock_data_by_period.py
oak/services/data_fetcher/api_service/library/stocks/fetch_stock_financials.py
oak/services/data_fetcher/api_service/library/stocks/fetch_stock_info.py
oak/services/data_fetcher/api_service/library/stocks/fetch_stock_news.py
oak/services/data_fetcher/database_service.py
oak/services/data_fetcher/dependencies.py
oak/services/data_fetcher/exceptions.py
oak/services/data_fetcher/prompt_service.py
oak/services/data_fetcher/rag_service.py
oak/tasks/library/__init__.py
oak/tasks/library/say_hello.py
oak/tasks/task_manager/__init__.py
oak/tools/__init__.py
oak/tools/financial_context.py
oak/utils/.DS_Store
oak/utils/__init__.py
oak/utils/agent/__init__.py
oak/utils/agent/base_agent_server.py
oak/utils/decorators/__init__.py
oak/utils/decorators/skill.py
oak/utils/helpers/__init__.py
oak/utils/helpers/html.py
oak/utils/helpers/markdown.py
oak/utils/helpers/serialization.py
oak_agent_core-0.1.17.dist-info/METADATA
oak_agent_core-0.1.17.dist-info/WHEEL
oak_agent_core-0.1.17.dist-info/RECORD
