Metadata-Version: 2.4
Name: oak-agent-core
Version: 0.1.17
Summary: A shared Python library for an agentic tool with a modular architecture, including a RAG service and financial data models.
License: MIT
Keywords: agentic,finance,rag,embeddings,ai
Author: Pumulo Sikaneta
Author-email: pumulo@gmail.com
Requires-Python: >=3.13.7,<4.0.0
Classifier: Development Status :: 3 - Alpha
Classifier: Intended Audience :: Developers
Classifier: Intended Audience :: Financial and Insurance Industry
Classifier: License :: OSI Approved :: MIT License
Classifier: Operating System :: OS Independent
Classifier: Programming Language :: Python :: 3
Classifier: Programming Language :: Python :: 3.14
Classifier: Programming Language :: Python :: 3.11
Classifier: Topic :: Scientific/Engineering :: Artificial Intelligence
Requires-Dist: Jinja2 (>=3.1.6,<4.0.0)
Requires-Dist: celery[redis] (>=5.3.6,<6.0.0)
Requires-Dist: fastapi (>=0.103.1,<0.104.0)
Requires-Dist: fastembed (>=0.7.3,<0.8.0)
Requires-Dist: langchain (==0.3.27)
Requires-Dist: psycopg2-binary (>=2.9.7,<3.0.0)
Requires-Dist: python-dotenv (>=1.0.0,<2.0.0)
Requires-Dist: redis (>=5.0.1,<6.0.0)
Requires-Dist: sqlalchemy (>=2.0.21,<3.0.0)
Requires-Dist: uvicorn[standard] (>=0.23.2,<0.24.0)
Project-URL: Documentation, https://oak-agent-core.readthedocs.io
Project-URL: Homepage, https://github.com/pumulo/oak-agent-core
Project-URL: Repository, https://github.com/pumulo/oak-agent-core
